hack4u/__init__.py
hack4u/course.py
hack4u/utils.py
hack4ufromrd-1.0.0.dist-info/METADATA
hack4ufromrd-1.0.0.dist-info/WHEEL
hack4ufromrd-1.0.0.dist-info/top_level.txt
hack4ufromrd-1.0.0.dist-info/RECORD
