Metadata-Version: 2.4
Name: Hack4ufromrd
Version: 1.0.0
Summary: Una biblioteca para consultar los cursos de hack4u de S4vitar
Home-page: https://hack4u.io/
Author: Cedric Santana
Dynamic: author
Dynamic: description
Dynamic: description-content-type
Dynamic: home-page
Dynamic: summary
